townwish_mindone_testing/__init__.py
townwish_mindone_testing/version.py
townwish_mindone_testing/data/__init__.py
townwish_mindone_testing/data/data_split.py
townwish_mindone_testing/data/dataset.py
townwish_mindone_testing/data/loader.py
townwish_mindone_testing/data/video_reader.py
townwish_mindone_testing/diffusers/README.md
townwish_mindone_testing/diffusers/__init__.py
townwish_mindone_testing/diffusers/callbacks.py
townwish_mindone_testing/diffusers/configuration_utils.py
townwish_mindone_testing/diffusers/image_processor.py
townwish_mindone_testing/diffusers/optimization.py
townwish_mindone_testing/diffusers/training_utils.py
townwish_mindone_testing/diffusers/video_processor.py
townwish_mindone_testing/diffusers/_peft/__init__.py
townwish_mindone_testing/diffusers/_peft/config.py
townwish_mindone_testing/diffusers/_peft/mapping.py
townwish_mindone_testing/diffusers/_peft/peft_model.py
townwish_mindone_testing/diffusers/_peft/tuners/__init__.py
townwish_mindone_testing/diffusers/_peft/tuners/tuners_utils.py
townwish_mindone_testing/diffusers/_peft/tuners/lora/__init__.py
townwish_mindone_testing/diffusers/_peft/tuners/lora/config.py
townwish_mindone_testing/diffusers/_peft/tuners/lora/layer.py
townwish_mindone_testing/diffusers/_peft/tuners/lora/model.py
townwish_mindone_testing/diffusers/_peft/utils/__init__.py
townwish_mindone_testing/diffusers/_peft/utils/constants.py
townwish_mindone_testing/diffusers/_peft/utils/other.py
townwish_mindone_testing/diffusers/_peft/utils/peft_types.py
townwish_mindone_testing/diffusers/_peft/utils/save_and_load.py
townwish_mindone_testing/diffusers/loaders/__init__.py
townwish_mindone_testing/diffusers/loaders/ip_adapter.py
townwish_mindone_testing/diffusers/loaders/lora.py
townwish_mindone_testing/diffusers/loaders/lora_conversion_utils.py
townwish_mindone_testing/diffusers/loaders/peft.py
townwish_mindone_testing/diffusers/loaders/single_file.py
townwish_mindone_testing/diffusers/loaders/single_file_model.py
townwish_mindone_testing-0.2.0.dist-info/METADATA
townwish_mindone_testing-0.2.0.dist-info/WHEEL
townwish_mindone_testing-0.2.0.dist-info/licenses/LICENSE
townwish_mindone_testing-0.2.0.dist-info/RECORD
